lpctorch/__init__.py
lpctorch/lpc.py
LPCTorch-0.1.4.dist-info/METADATA
LPCTorch-0.1.4.dist-info/WHEEL
LPCTorch-0.1.4.dist-info/top_level.txt
LPCTorch-0.1.4.dist-info/RECORD
