Metadata-Version: 2.1
Name: LPCTorch
Version: 0.1.4
Summary: LPC Utility for Pytorch Library.
Home-page: https://github.com/TowardHumanizedInteraction/LPCTorch
Author: yliess
Author-email: hatiyliess86@gmail.com
License: MIT
Platform: UNKNOWN
Requires-Python: >=3.4, <4
Requires-Dist: numpy (==1.17.2)
Requires-Dist: torch (==1.2.0)
Requires-Dist: torchaudio (==0.3.0)
Requires-Dist: tqdm (==4.36.1)
Requires-Dist: matplotlib (==3.0.1)
Requires-Dist: librosa (==0.7.1)
